<annotation>
	<folder>image</folder>
	<filename>IMG20211227133908_BURST000.jpg</filename>
	<path>C:\Users\ujjwa\OneDrive\Desktop\project\train\image\IMG20211227133908_BURST000.jpg</path>
	<source>
		<database>Unknown</database>
	</source>
	<size>
		<width>3456</width>
		<height>4608</height>
		<depth>3</depth>
	</size>
	<segmented>0</segmented>
	<object>
		<name>blazer</name>
		<pose>Unspecified</pose>
		<truncated>0</truncated>
		<difficult>0</difficult>
		<bndbox>
			<xmin>646</xmin>
			<ymin>1064</ymin>
			<xmax>2120</xmax>
			<ymax>2727</ymax>
		</bndbox>
	</object>
	<object>
		<name>tie</name>
		<pose>Unspecified</pose>
		<truncated>0</truncated>
		<difficult>0</difficult>
		<bndbox>
			<xmin>1210</xmin>
			<ymin>1148</ymin>
			<xmax>1489</xmax>
			<ymax>1648</ymax>
		</bndbox>
	</object>
	<object>
		<name>pant</name>
		<pose>Unspecified</pose>
		<truncated>0</truncated>
		<difficult>0</difficult>
		<bndbox>
			<xmin>994</xmin>
			<ymin>2438</ymin>
			<xmax>1915</xmax>
			<ymax>4059</ymax>
		</bndbox>
	</object>
</annotation>
