<annotation>
	<folder>image</folder>
	<filename>IMG20211227133908_BURST012.jpg</filename>
	<path>C:\Users\ujjwa\OneDrive\Desktop\project\train\image\IMG20211227133908_BURST012.jpg</path>
	<source>
		<database>Unknown</database>
	</source>
	<size>
		<width>3456</width>
		<height>4608</height>
		<depth>3</depth>
	</size>
	<segmented>0</segmented>
	<object>
		<name>blazer</name>
		<pose>Unspecified</pose>
		<truncated>0</truncated>
		<difficult>0</difficult>
		<bndbox>
			<xmin>1567</xmin>
			<ymin>1138</ymin>
			<xmax>2873</xmax>
			<ymax>2627</ymax>
		</bndbox>
	</object>
	<object>
		<name>tie</name>
		<pose>Unspecified</pose>
		<truncated>0</truncated>
		<difficult>0</difficult>
		<bndbox>
			<xmin>2067</xmin>
			<ymin>1243</ymin>
			<xmax>2294</xmax>
			<ymax>1680</ymax>
		</bndbox>
	</object>
	<object>
		<name>pant</name>
		<pose>Unspecified</pose>
		<truncated>0</truncated>
		<difficult>0</difficult>
		<bndbox>
			<xmin>1857</xmin>
			<ymin>2401</ymin>
			<xmax>2625</xmax>
			<ymax>3948</ymax>
		</bndbox>
	</object>
</annotation>
