<annotation>
	<folder>image</folder>
	<filename>IMG20211227132204_BURST012.jpg</filename>
	<path>C:\Users\ujjwa\OneDrive\Desktop\project\train\image\IMG20211227132204_BURST012.jpg</path>
	<source>
		<database>Unknown</database>
	</source>
	<size>
		<width>3456</width>
		<height>4608</height>
		<depth>3</depth>
	</size>
	<segmented>0</segmented>
	<object>
		<name>blazer</name>
		<pose>Unspecified</pose>
		<truncated>0</truncated>
		<difficult>0</difficult>
		<bndbox>
			<xmin>1131</xmin>
			<ymin>948</ymin>
			<xmax>2567</xmax>
			<ymax>2843</ymax>
		</bndbox>
	</object>
	<object>
		<name>tie</name>
		<pose>Unspecified</pose>
		<truncated>0</truncated>
		<difficult>0</difficult>
		<bndbox>
			<xmin>1799</xmin>
			<ymin>1406</ymin>
			<xmax>2099</xmax>
			<ymax>2332</ymax>
		</bndbox>
	</object>
	<object>
		<name>pant</name>
		<pose>Unspecified</pose>
		<truncated>0</truncated>
		<difficult>0</difficult>
		<bndbox>
			<xmin>1452</xmin>
			<ymin>2295</ymin>
			<xmax>2241</xmax>
			<ymax>4143</ymax>
		</bndbox>
	</object>
</annotation>
